{
  "gitSyncId": "670633b163d5690c2f531ce9_16e099c5-71da-4295-b1c3-3ab52eb12487",
  "id": "Home_functions.initLoad",
  "pluginId": "js-plugin",
  "pluginType": "JS",
  "unpublishedAction": {
    "actionConfiguration": {
      "encodeParamsToggle": true,
      "jsArguments": [],
      "paginationType": "NONE",
      "timeoutInMillisecond": 10000
    },
    "collectionId": "Home_functions",
    "confirmBeforeExecute": false,
    "datasource": {
      "isAutoGenerated": false,
      "name": "UNUSED_DATASOURCE",
      "pluginId": "js-plugin"
    },
    "dynamicBindingPathList": [
      {
        "key": "body"
      }
    ],
    "executeOnLoad": true,
    "fullyQualifiedName": "functions.initLoad",
    "name": "initLoad",
    "pageId": "Home",
    "userSetOnLoad": true
  }
}